pywear/__init__.py
pywear/skeleton.py
pywear-0.0.1.dist-info/AUTHORS.rst
pywear-0.0.1.dist-info/LICENSE.txt
pywear-0.0.1.dist-info/METADATA
pywear-0.0.1.dist-info/WHEEL
pywear-0.0.1.dist-info/top_level.txt
pywear-0.0.1.dist-info/RECORD
